dmtgenfor/__init__.py
dmtgenfor/generator.py
dmtgenfor/generators/__init__.py
dmtgenfor/generators/graph.py
dmtgenfor/generators/runtime_generator.py
dmtgenfor/generators/dmt/__init__.py
dmtgenfor/generators/dmt/common.py
dmtgenfor/generators/dmt/package_generator.py
dmtgenfor/generators/dmt/type_generator.py
dmtgenfor/generators/simos/__init__.py
dmtgenfor/generators/simos/common.py
dmtgenfor/generators/simos/entity_model.py
dmtgenfor/generators/simos/resize_model.py
dmtgenfor/generators/simos/simos.py
dmtgenfor/generators/simos/simos_entity_generator.py
dmtgenfor/generators/simos/simos_package_generator.py
dmtgenfor/generators/simos/simos_sourcelist_generator.py
dmtgenfor/templates/package.f90.jinja
dmtgenfor/templates/simos.F90.jinja
dmtgenfor/templates/simos_package.F90.jinja
dmtgenfor/templates/simos_sources.cmake.jinja
dmtgenfor/templates/type.f90.jinja
dmtgenfor-0.7.3.dist-info/LICENSE
dmtgenfor-0.7.3.dist-info/METADATA
dmtgenfor-0.7.3.dist-info/WHEEL
dmtgenfor-0.7.3.dist-info/top_level.txt
dmtgenfor-0.7.3.dist-info/RECORD
