Metadata-Version: 2.2
Name: dmtgenfor
Version: 0.7.3
Summary: Fortran generator for DMT based models
Author: SINTEF Ocean
Classifier: Programming Language :: Python :: 3
Classifier: License :: OSI Approved :: MIT License
Classifier: Operating System :: OS Independent
Requires-Python: >=3.8
License-File: LICENSE
Requires-Dist: jinja2==3.1.3
Requires-Dist: dmtgen==0.5.0
Requires-Dist: inflection==0.5.1
Dynamic: author
Dynamic: classifier
Dynamic: description
Dynamic: description-content-type
Dynamic: requires-dist
Dynamic: requires-python
Dynamic: summary
